garf/core/__init__.py
garf/core/api_clients.py
garf/core/base_query.py
garf/core/cache.py
garf/core/exceptions.py
garf/core/parsers.py
garf/core/query_editor.py
garf/core/query_parser.py
garf/core/report.py
garf/core/report_fetcher.py
garf/core/simulator.py
garf/core/telemetry.py
garf/core/fetchers/__init__.py
garf/core/fetchers/fake.py
garf/core/fetchers/rest.py
garf_core/__init__.py
garf_core/api_clients.py
garf_core/base_query.py
garf_core/cache.py
garf_core/exceptions.py
garf_core/parsers.py
garf_core/query_editor.py
garf_core/query_parser.py
garf_core/report.py
garf_core/report_fetcher.py
garf_core/simulator.py
garf_core/telemetry.py
garf_core/fetchers/__init__.py
garf_core/fetchers/fake.py
garf_core/fetchers/rest.py
garf_core-1.0.1.dist-info/METADATA
garf_core-1.0.1.dist-info/WHEEL
garf_core-1.0.1.dist-info/entry_points.txt
garf_core-1.0.1.dist-info/top_level.txt
garf_core-1.0.1.dist-info/RECORD
