Metadata-Version: 2.4
Name: garf-core
Version: 1.0.1
Summary: Abstracts fetching data from API based on provided SQL-like query.
Author-email: "Google Inc. (gTech gPS CSE team)" <no-reply@google.com>, Andrei Markin <andrey.markin.ppc@gmail.com>
License: Apache 2.0
Classifier: Programming Language :: Python :: 3 :: Only
Classifier: Programming Language :: Python :: 3.9
Classifier: Programming Language :: Python :: 3.10
Classifier: Programming Language :: Python :: 3.11
Classifier: Programming Language :: Python :: 3.12
Classifier: Programming Language :: Python :: 3.13
Classifier: Programming Language :: Python :: 3.14
Classifier: Intended Audience :: Developers
Classifier: Topic :: Software Development :: Libraries :: Python Modules
Classifier: Operating System :: OS Independent
Classifier: License :: OSI Approved :: Apache Software License
Requires-Python: >=3.9
Requires-Dist: python-dateutil
Requires-Dist: jinja2
Requires-Dist: typing-extensions
Requires-Dist: requests
Requires-Dist: pyyaml
Requires-Dist: pydantic
Requires-Dist: eval_type_backport
Requires-Dist: opentelemetry-api
Provides-Extra: pandas
Requires-Dist: pandas; extra == "pandas"
Provides-Extra: polars
Requires-Dist: polars; extra == "polars"
Provides-Extra: all
Requires-Dist: garf-core[pandas,polars]; extra == "all"
